README.rst
setup.cfg
setup.py
nagios_audit/__init__.py
nagios_audit/cli.py
nagios_audit/core.py
nagios_audit/presentation.py
nagios_audit.egg-info/PKG-INFO
nagios_audit.egg-info/SOURCES.txt
nagios_audit.egg-info/dependency_links.txt
nagios_audit.egg-info/entry_points.txt
nagios_audit.egg-info/requires.txt
nagios_audit.egg-info/top_level.txt