Metadata-Version: 1.1
Name: nagios-audit
Version: 1.0.6
Summary: Nagios CLI utility for auditing purposes.
Home-page: https://github.com/bingoarun/nagios-audit
Author: Arun prasath
Author-email: arunprasath33@gmail.com
License: MIT
Keywords: Monitoring auditing nagios
Platform: UNKNOWN
Classifier: Development Status :: 1 - Planning
Classifier: Intended Audience :: System Administrators
Classifier: Topic :: System :: Monitoring
Classifier: License :: OSI Approved :: MIT License
Classifier: Programming Language :: Python :: 2
Classifier: Programming Language :: Python :: 2.6
Classifier: Programming Language :: Python :: 2.7
Classifier: Programming Language :: Python :: 3
Classifier: Programming Language :: Python :: 3.2
Classifier: Programming Language :: Python :: 3.3
Classifier: Programming Language :: Python :: 3.4
